py_superops/__init__.py
py_superops/auth.py
py_superops/cli.py
py_superops/client.py
py_superops/config.py
py_superops/exceptions.py
py_superops/py.typed
py_superops/graphql/__init__.py
py_superops/graphql/builder.py
py_superops/graphql/fragments.py
py_superops/graphql/queries.py
py_superops/graphql/types.py
py_superops/managers/__init__.py
py_superops/managers/assets.py
py_superops/managers/attachments.py
py_superops/managers/automation_manager.py
py_superops/managers/base.py
py_superops/managers/clients.py
py_superops/managers/comments.py
py_superops/managers/contacts.py
py_superops/managers/contracts.py
py_superops/managers/knowledge_base.py
py_superops/managers/monitoring_manager.py
py_superops/managers/projects.py
py_superops/managers/scripts_manager.py
py_superops/managers/sites.py
py_superops/managers/tasks.py
py_superops/managers/tickets.py
py_superops/managers/time_entries.py
py_superops/managers/users.py
py_superops/managers/webhooks.py
py_superops-0.2.9.dist-info/METADATA
py_superops-0.2.9.dist-info/WHEEL
py_superops-0.2.9.dist-info/entry_points.txt
py_superops-0.2.9.dist-info/licenses/LICENSE
py_superops-0.2.9.dist-info/RECORD
