Metadata-Version: 2.4
Name: py-superops
Version: 0.2.9
Summary: Python client library for the SuperOps GraphQL API with async support, type safety, and comprehensive error handling
Project-URL: Homepage, https://github.com/asachs01/py-superops
Project-URL: Documentation, https://py-superops.readthedocs.io
Project-URL: Repository, https://github.com/asachs01/py-superops.git
Project-URL: Issues, https://github.com/asachs01/py-superops/issues
Project-URL: Changelog, https://github.com/asachs01/py-superops/blob/main/CHANGELOG.md
Author-email: Aaron Sachs <aaron@wyre.com>
Maintainer-email: Aaron Sachs <aaron@wyre.com>
License: MIT
License-File: LICENSE
Keywords: api,async,client-library,graphql,msp,psa,rmm,superops
Classifier: Development Status :: 4 - Beta
Classifier: Intended Audience :: Developers
Classifier: License :: OSI Approved :: MIT License
Classifier: Operating System :: OS Independent
Classifier: Programming Language :: Python :: 3
Classifier: Programming Language :: Python :: 3.8
Classifier: Programming Language :: Python :: 3.9
Classifier: Programming Language :: Python :: 3.10
Classifier: Programming Language :: Python :: 3.11
Classifier: Programming Language :: Python :: 3.12
Classifier: Topic :: Internet :: WWW/HTTP :: Dynamic Content
Classifier: Topic :: Office/Business
Classifier: Topic :: Software Development :: Libraries :: Python Modules
Classifier: Topic :: System :: Systems Administration
Classifier: Typing :: Typed
Requires-Python: >=3.8
Requires-Dist: aiofiles<24.0.0,>=23.0.0
Requires-Dist: aiohttp<4.0.0,>=3.8.0
Requires-Dist: click<9.0.0,>=8.0.0
Requires-Dist: httpx<1.0.0,>=0.24.0
Requires-Dist: pydantic-settings<3.0.0,>=2.0.0
Requires-Dist: pydantic<3.0.0,>=2.0.0
Requires-Dist: rich<14.0.0,>=13.0.0
Requires-Dist: typing-extensions>=4.0.0; python_version < '3.10'
Provides-Extra: dev
Requires-Dist: bandit[toml]>=1.7.0; extra == 'dev'
Requires-Dist: black>=22.0.0; extra == 'dev'
Requires-Dist: build>=1.0.0; extra == 'dev'
Requires-Dist: cyclonedx-bom>=4.0.0; extra == 'dev'
Requires-Dist: flake8-bandit>=4.1.0; extra == 'dev'
Requires-Dist: flake8-bugbear>=23.0.0; extra == 'dev'
Requires-Dist: flake8-comprehensions>=3.14.0; extra == 'dev'
Requires-Dist: flake8-docstrings>=1.7.0; extra == 'dev'
Requires-Dist: flake8-pytest-style>=1.7.0; extra == 'dev'
Requires-Dist: flake8-simplify>=0.21.0; extra == 'dev'
Requires-Dist: flake8>=5.0.0; extra == 'dev'
Requires-Dist: isort>=5.12.0; extra == 'dev'
Requires-Dist: licensecheck>=2023.1.1; extra == 'dev'
Requires-Dist: mypy>=1.0.0; extra == 'dev'
Requires-Dist: pip-audit>=2.6.0; extra == 'dev'
Requires-Dist: pip-licenses>=4.3.0; extra == 'dev'
Requires-Dist: pre-commit>=2.20.0; extra == 'dev'
Requires-Dist: pydocstyle[toml]>=6.3.0; extra == 'dev'
Requires-Dist: pytest-asyncio>=0.21.0; extra == 'dev'
Requires-Dist: pytest-benchmark>=4.0.0; extra == 'dev'
Requires-Dist: pytest-cov>=4.0.0; extra == 'dev'
Requires-Dist: pytest-mock>=3.10.0; extra == 'dev'
Requires-Dist: pytest-xdist>=3.0.0; extra == 'dev'
Requires-Dist: pytest>=7.0.0; extra == 'dev'
Requires-Dist: python-semantic-release>=8.0.0; extra == 'dev'
Requires-Dist: respx>=0.20.0; extra == 'dev'
Requires-Dist: ruff>=0.1.0; extra == 'dev'
Requires-Dist: safety>=3.0.0; extra == 'dev'
Requires-Dist: semgrep>=1.45.0; extra == 'dev'
Requires-Dist: tox>=4.0.0; extra == 'dev'
Requires-Dist: twine>=4.0.0; extra == 'dev'
Requires-Dist: types-pyyaml>=6.0.0; extra == 'dev'
Requires-Dist: types-requests>=2.31.0; extra == 'dev'
Provides-Extra: docs
Requires-Dist: myst-parser>=0.18.0; extra == 'docs'
Requires-Dist: sphinx-autodoc-typehints>=1.19.0; extra == 'docs'
Requires-Dist: sphinx-rtd-theme>=1.2.0; extra == 'docs'
Requires-Dist: sphinx>=5.0.0; extra == 'docs'
Provides-Extra: examples
Requires-Dist: aiofiles>=22.1.0; extra == 'examples'
Requires-Dist: asyncio-mqtt>=0.13.0; extra == 'examples'
Requires-Dist: rich>=13.0.0; extra == 'examples'
Provides-Extra: yaml
Requires-Dist: pyyaml>=6.0.0; extra == 'yaml'
